info_llm_observe/__init__.py
info_llm_observe/client.py
info_llm_observe/decorators.py
info_llm_observe/exceptions.py
info_llm_observe/registry.py
info_llm_observe/utils.py
info_llm_observe/version.py
info_llm_observe/providers/base.py
info_llm_observe/providers/phoenix_provider.py
info_llm_observe-0.2.3.dist-info/licenses/LICENSE
info_llm_observe-0.2.3.dist-info/METADATA
info_llm_observe-0.2.3.dist-info/WHEEL
info_llm_observe-0.2.3.dist-info/top_level.txt
info_llm_observe-0.2.3.dist-info/RECORD
