Metadata-Version: 2.4
Name: info-llm-observe
Version: 0.2.3
Summary: A small observability wrapper for LLM projects (Phoenix adapter included)
Author-email: Your Name <you@example.com>
Requires-Python: >=3.8
License-File: LICENSE
Requires-Dist: requests>=2.28
Dynamic: license-file
